mdformat_clang/__init__.py
mdformat_clang/plugin.py
mdformat_clang-0.0.1.dist-info/entry_points.txt
mdformat_clang-0.0.1.dist-info/licenses/LICENSE
mdformat_clang-0.0.1.dist-info/WHEEL
mdformat_clang-0.0.1.dist-info/METADATA
mdformat_clang-0.0.1.dist-info/RECORD
