Metadata-Version: 2.4
Name: mdformat_clang
Version: 0.0.1
Summary: An mdformat plugin for any language supported by clang-format
Keywords: mdformat,markdown,markdown-it
Author-email: Chris Glover <c.d.glover@gmail.com>
Requires-Python: >=3.7
Classifier: Intended Audience :: Developers
Classifier: License :: OSI Approved :: MIT License
Classifier: Programming Language :: Python :: 3
Classifier: Topic :: Software Development :: Libraries :: Python Modules
License-File: LICENSE
Requires-Dist: mdformat >=0.7.0,<0.8.0
Requires-Dist: pre-commit ; extra == "dev"
Requires-Dist: pytest~=6.0 ; extra == "test"
Requires-Dist: coverage ; extra == "test"
Requires-Dist: pytest-cov ; extra == "test"
Project-URL: Homepage, https://github.com/cdglove/mdformat-clang
Provides-Extra: dev
Provides-Extra: test
